{
  "info": {
    "_postman_id": "f8a2c9e1-3b4d-5f6a-7890-abcdef123456",
    "name": "Ecommerce Microservice",
    "description": "Professional Postman collection for testing and demoing the ecommerce microservice endpoints, exposed through the API gateway on port 8080. Requests are grouped by service and feature, covering authentication flows, user profile management, and fine-grained RBAC (roles, permissions, role-permission assignment, and user-role assignment). Run Authentication / Register User and Authentication / Login Admin first to populate the token variables used by all secured requests.",
    "schema": "https://schema.getpostman.com/json/collection/v2.1.0/collection.json"
  },
  "item": [
    {
      "name": "Authentication",
      "item": [
        {
          "name": "Register User",
          "event": [
            {
              "listen": "prerequest",
              "script": {
                "exec": [
                  "const uniqueSuffix = Date.now();",
                  "pm.collectionVariables.set('AUTH_FIRST_NAME', 'Pial');",
                  "pm.collectionVariables.set('AUTH_LAST_NAME', 'Samadder');",
                  "pm.collectionVariables.set('AUTH_USERNAME', `pial_${uniqueSuffix}`);",
                  "pm.collectionVariables.set('AUTH_EMAIL', `pial_${uniqueSuffix}@example.com`);",
                  "pm.collectionVariables.set('AUTH_PHONE_NUMBER', '+8801700000000');",
                  "pm.collectionVariables.set('AUTH_PASSWORD', 'StrongPass123');"
                ],
                "type": "text/javascript",
                "packages": {},
                "requests": {}
              }
            },
            {
              "listen": "test",
              "script": {
                "exec": [
                  "const response = pm.response.json();",
                  "if (response.data && response.data.id) {",
                  "    pm.collectionVariables.set('AUTH_USER_ID', response.data.id);",
                  "}"
                ],
                "type": "text/javascript",
                "packages": {},
                "requests": {}
              }
            }
          ],
          "request": {
            "method": "POST",
            "header": [
              { "key": "Content-Type", "value": "application/json" },
              { "key": "Accept", "value": "application/json" }
            ],
            "body": {
              "mode": "raw",
              "raw": "{\n  \"firstName\": \"{{AUTH_FIRST_NAME}}\",\n  \"lastName\": \"{{AUTH_LAST_NAME}}\",\n  \"username\": \"{{AUTH_USERNAME}}\",\n  \"email\": \"{{AUTH_EMAIL}}\",\n  \"phoneNumber\": \"{{AUTH_PHONE_NUMBER}}\",\n  \"password\": \"{{AUTH_PASSWORD}}\"\n}"
            },
            "url": {
              "raw": "{{BASE_URL}}/api/v1/auth/register",
              "host": ["{{BASE_URL}}"],
              "path": ["api", "v1", "auth", "register"]
            },
            "description": "Registers a new active user account. This endpoint is public and does not require a bearer token. A unique username and email are generated via a timestamp suffix so the request can be run repeatedly without conflicts."
          },
          "response": []
        },
        {
          "name": "Login User",
          "event": [
            {
              "listen": "test",
              "script": {
                "exec": [
                  "const response = pm.response.json();",
                  "if (response.data) {",
                  "    pm.collectionVariables.set('ACCESS_TOKEN', response.data.accessToken);",
                  "    pm.collectionVariables.set('REFRESH_TOKEN', response.data.refreshToken);",
                  "    pm.collectionVariables.set('TOKEN_TYPE', response.data.tokenType || 'Bearer');",
                  "}"
                ],
                "type": "text/javascript",
                "packages": {},
                "requests": {}
              }
            }
          ],
          "request": {
            "method": "POST",
            "header": [
              { "key": "Content-Type", "value": "application/json" },
              { "key": "Accept", "value": "application/json" }
            ],
            "body": {
              "mode": "raw",
              "raw": "{\n  \"username\": \"{{AUTH_USERNAME}}\",\n  \"password\": \"{{AUTH_PASSWORD}}\"\n}"
            },
            "url": {
              "raw": "{{BASE_URL}}/api/v1/auth/login",
              "host": ["{{BASE_URL}}"],
              "path": ["api", "v1", "auth", "login"]
            },
            "description": "Authenticates a registered user and stores the returned access and refresh tokens as ACCESS_TOKEN and REFRESH_TOKEN for use in user-scoped endpoints."
          },
          "response": []
        },
        {
          "name": "Login Admin",
          "event": [
            {
              "listen": "test",
              "script": {
                "exec": [
                  "const response = pm.response.json();",
                  "if (response.data) {",
                  "    pm.collectionVariables.set('ADMIN_ACCESS_TOKEN', response.data.accessToken);",
                  "    pm.collectionVariables.set('ADMIN_REFRESH_TOKEN', response.data.refreshToken);",
                  "    pm.collectionVariables.set('TOKEN_TYPE', response.data.tokenType || 'Bearer');",
                  "}"
                ],
                "type": "text/javascript",
                "packages": {},
                "requests": {}
              }
            }
          ],
          "request": {
            "method": "POST",
            "header": [
              { "key": "Content-Type", "value": "application/json" },
              { "key": "Accept", "value": "application/json" }
            ],
            "body": {
              "mode": "raw",
              "raw": "{\n  \"username\": \"{{ADMIN_USERNAME}}\",\n  \"password\": \"{{ADMIN_PASSWORD}}\"\n}"
            },
            "url": {
              "raw": "{{BASE_URL}}/api/v1/auth/login",
              "host": ["{{BASE_URL}}"],
              "path": ["api", "v1", "auth", "login"]
            },
            "description": "Authenticates the seeded demo administrator and stores admin tokens as ADMIN_ACCESS_TOKEN and ADMIN_REFRESH_TOKEN for all secured /api/v1/admin requests."
          },
          "response": []
        },
        {
          "name": "Refresh Token",
          "event": [
            {
              "listen": "test",
              "script": {
                "exec": [
                  "const response = pm.response.json();",
                  "if (response.data) {",
                  "    pm.collectionVariables.set('ACCESS_TOKEN', response.data.accessToken);",
                  "    pm.collectionVariables.set('REFRESH_TOKEN', response.data.refreshToken);",
                  "    pm.collectionVariables.set('TOKEN_TYPE', response.data.tokenType || 'Bearer');",
                  "}"
                ],
                "type": "text/javascript",
                "packages": {},
                "requests": {}
              }
            }
          ],
          "request": {
            "method": "POST",
            "header": [
              { "key": "Content-Type", "value": "application/json" },
              { "key": "Accept", "value": "application/json" }
            ],
            "body": {
              "mode": "raw",
              "raw": "{\n  \"refreshToken\": \"{{REFRESH_TOKEN}}\"\n}"
            },
            "url": {
              "raw": "{{BASE_URL}}/api/v1/auth/refresh",
              "host": ["{{BASE_URL}}"],
              "path": ["api", "v1", "auth", "refresh"]
            },
            "description": "Rotates the refresh token and stores the newly returned access and refresh token pair. The old refresh token is revoked server-side. This endpoint is public and does not require a bearer token."
          },
          "response": []
        },
        {
          "name": "Logout User",
          "event": [],
          "request": {
            "method": "POST",
            "header": [
              { "key": "Content-Type", "value": "application/json" },
              { "key": "Accept", "value": "application/json" },
              { "key": "Authorization", "value": "Bearer {{ACCESS_TOKEN}}" }
            ],
            "body": {
              "mode": "raw",
              "raw": "{\n  \"refreshToken\": \"{{REFRESH_TOKEN}}\"\n}"
            },
            "url": {
              "raw": "{{BASE_URL}}/api/v1/auth/logout",
              "host": ["{{BASE_URL}}"],
              "path": ["api", "v1", "auth", "logout"]
            },
            "description": "Logs out the authenticated user by revoking the submitted refresh token and blacklisting the active access token in Redis. Requires a valid bearer token in the Authorization header."
          },
          "response": []
        }
      ]
    },
    {
      "name": "User Profile",
      "item": [
        {
          "name": "Happy Path",
          "item": [
            {
              "name": "Get Current User Profile",
              "event": [
                {
                  "listen": "test",
                  "script": {
                    "exec": [
                      "const response = pm.response.json();",
                      "if (response.data && response.data.id) {",
                      "    pm.collectionVariables.set('AUTH_USER_ID', response.data.id);",
                      "}"
                    ],
                    "type": "text/javascript",
                    "packages": {},
                    "requests": {}
                  }
                }
              ],
              "request": {
                "method": "GET",
                "header": [
                  { "key": "Accept", "value": "application/json" },
                  { "key": "Authorization", "value": "Bearer {{ACCESS_TOKEN}}" }
                ],
                "url": {
                  "raw": "{{BASE_URL}}/api/v1/users/me",
                  "host": ["{{BASE_URL}}"],
                  "path": ["api", "v1", "users", "me"]
                },
                "description": "Retrieves the authenticated user's own profile. The API gateway automatically forwards the user identity via the X-User-Id header so no additional header is needed from the client."
              },
              "response": []
            },
            {
              "name": "Update Current User Profile",
              "event": [
                {
                  "listen": "prerequest",
                  "script": {
                    "exec": [
                      "pm.collectionVariables.set('UPDATED_FIRST_NAME', 'PialUpdated');",
                      "pm.collectionVariables.set('UPDATED_PHONE_NUMBER', '+8801711111111');"
                    ],
                    "type": "text/javascript",
                    "packages": {},
                    "requests": {}
                  }
                }
              ],
              "request": {
                "method": "PUT",
                "header": [
                  { "key": "Content-Type", "value": "application/json" },
                  { "key": "Accept", "value": "application/json" },
                  { "key": "Authorization", "value": "Bearer {{ACCESS_TOKEN}}" }
                ],
                "body": {
                  "mode": "raw",
                  "raw": "{\n  \"firstName\": \"{{UPDATED_FIRST_NAME}}\",\n  \"lastName\": \"Samadder\",\n  \"phoneNumber\": \"{{UPDATED_PHONE_NUMBER}}\"\n}"
                },
                "url": {
                  "raw": "{{BASE_URL}}/api/v1/users/me",
                  "host": ["{{BASE_URL}}"],
                  "path": ["api", "v1", "users", "me"]
                },
                "description": "Updates the authenticated user's own profile fields (firstName, lastName, phoneNumber). Username and email are immutable."
              },
              "response": []
            },
            {
              "name": "Change Password",
              "event": [
                {
                  "listen": "prerequest",
                  "script": {
                    "exec": [
                      "if (!pm.collectionVariables.get('AUTH_PASSWORD')) {",
                      "    throw new Error('Run Authentication / Register User first so AUTH_PASSWORD is available.');",
                      "}"
                    ],
                    "type": "text/javascript",
                    "packages": {},
                    "requests": {}
                  }
                }
              ],
              "request": {
                "method": "POST",
                "header": [
                  { "key": "Content-Type", "value": "application/json" },
                  { "key": "Accept", "value": "application/json" },
                  { "key": "Authorization", "value": "Bearer {{ACCESS_TOKEN}}" }
                ],
                "body": {
                  "mode": "raw",
                  "raw": "{\n  \"currentPassword\": \"{{AUTH_PASSWORD}}\",\n  \"newPassword\": \"StrongNewPass456\",\n  \"confirmPassword\": \"StrongNewPass456\"\n}"
                },
                "url": {
                  "raw": "{{BASE_URL}}/api/v1/users/me/password",
                  "host": ["{{BASE_URL}}"],
                  "path": ["api", "v1", "users", "me", "password"]
                },
                "description": "Changes the authenticated user's password after verifying the current password. The newPassword and confirmPassword fields must match and the new password must be at least 8 characters."
              },
              "response": []
            }
          ]
        },
        {
          "name": "Validation And Error Scenarios",
          "item": [
            {
              "name": "Get Profile - Unauthorized",
              "event": [],
              "request": {
                "method": "GET",
                "header": [
                  { "key": "Accept", "value": "application/json" }
                ],
                "url": {
                  "raw": "{{BASE_URL}}/api/v1/users/me",
                  "host": ["{{BASE_URL}}"],
                  "path": ["api", "v1", "users", "me"]
                },
                "description": "Verifies that the profile endpoint returns 401 when no bearer token is supplied."
              },
              "response": []
            },
            {
              "name": "Update Profile - Blank First Name",
              "event": [],
              "request": {
                "method": "PUT",
                "header": [
                  { "key": "Content-Type", "value": "application/json" },
                  { "key": "Accept", "value": "application/json" },
                  { "key": "Authorization", "value": "Bearer {{ACCESS_TOKEN}}" }
                ],
                "body": {
                  "mode": "raw",
                  "raw": "{\n  \"firstName\": \"\",\n  \"lastName\": \"Samadder\",\n  \"phoneNumber\": \"+8801700000000\"\n}"
                },
                "url": {
                  "raw": "{{BASE_URL}}/api/v1/users/me",
                  "host": ["{{BASE_URL}}"],
                  "path": ["api", "v1", "users", "me"]
                },
                "description": "Validates that firstName is required and cannot be blank for profile updates."
              },
              "response": []
            },
            {
              "name": "Change Password - Mismatched Confirm",
              "event": [],
              "request": {
                "method": "POST",
                "header": [
                  { "key": "Content-Type", "value": "application/json" },
                  { "key": "Accept", "value": "application/json" },
                  { "key": "Authorization", "value": "Bearer {{ACCESS_TOKEN}}" }
                ],
                "body": {
                  "mode": "raw",
                  "raw": "{\n  \"currentPassword\": \"{{AUTH_PASSWORD}}\",\n  \"newPassword\": \"StrongNewPass456\",\n  \"confirmPassword\": \"DoesNotMatch789\"\n}"
                },
                "url": {
                  "raw": "{{BASE_URL}}/api/v1/users/me/password",
                  "host": ["{{BASE_URL}}"],
                  "path": ["api", "v1", "users", "me", "password"]
                },
                "description": "Validates that newPassword and confirmPassword must match."
              },
              "response": []
            },
            {
              "name": "Change Password - Wrong Current Password",
              "event": [],
              "request": {
                "method": "POST",
                "header": [
                  { "key": "Content-Type", "value": "application/json" },
                  { "key": "Accept", "value": "application/json" },
                  { "key": "Authorization", "value": "Bearer {{ACCESS_TOKEN}}" }
                ],
                "body": {
                  "mode": "raw",
                  "raw": "{\n  \"currentPassword\": \"WrongCurrentPass999\",\n  \"newPassword\": \"StrongNewPass456\",\n  \"confirmPassword\": \"StrongNewPass456\"\n}"
                },
                "url": {
                  "raw": "{{BASE_URL}}/api/v1/users/me/password",
                  "host": ["{{BASE_URL}}"],
                  "path": ["api", "v1", "users", "me", "password"]
                },
                "description": "Validates that an incorrect current password is rejected with 401."
              },
              "response": []
            },
            {
              "name": "Change Password - Too Short New Password",
              "event": [],
              "request": {
                "method": "POST",
                "header": [
                  { "key": "Content-Type", "value": "application/json" },
                  { "key": "Accept", "value": "application/json" },
                  { "key": "Authorization", "value": "Bearer {{ACCESS_TOKEN}}" }
                ],
                "body": {
                  "mode": "raw",
                  "raw": "{\n  \"currentPassword\": \"{{AUTH_PASSWORD}}\",\n  \"newPassword\": \"short\",\n  \"confirmPassword\": \"short\"\n}"
                },
                "url": {
                  "raw": "{{BASE_URL}}/api/v1/users/me/password",
                  "host": ["{{BASE_URL}}"],
                  "path": ["api", "v1", "users", "me", "password"]
                },
                "description": "Validates that the new password must be at least 8 characters long."
              },
              "response": []
            }
          ]
        }
      ]
    },
    {
      "name": "RBAC Management",
      "item": [
        {
          "name": "Roles",
          "item": [
            {
              "name": "List Roles",
              "event": [
                {
                  "listen": "test",
                  "script": {
                    "exec": [
                      "const response = pm.response.json();",
                      "const roles = response.data && response.data.content ? response.data.content : [];",
                      "const role = roles.find(item => item.code === pm.collectionVariables.get('ROLE_CODE')) || roles[0];",
                      "if (role && role.id) {",
                      "    pm.collectionVariables.set('ROLE_ID', role.id);",
                      "}"
                    ],
                    "type": "text/javascript",
                    "packages": {},
                    "requests": {}
                  }
                }
              ],
              "request": {
                "method": "GET",
                "header": [
                  { "key": "Accept", "value": "application/json" },
                  { "key": "Authorization", "value": "Bearer {{ADMIN_ACCESS_TOKEN}}" }
                ],
                "url": {
                  "raw": "{{BASE_URL}}/api/v1/admin/roles?page=0&size=10",
                  "host": ["{{BASE_URL}}"],
                  "path": ["api", "v1", "admin", "roles"],
                  "query": [
                    { "key": "page", "value": "0" },
                    { "key": "size", "value": "10" }
                  ]
                },
                "description": "Lists RBAC roles with zero-based pagination. Requires ROLE_READ permission. The test script seeds ROLE_ID from the first matching result."
              },
              "response": []
            },
            {
              "name": "Get Role By ID",
              "event": [
                {
                  "listen": "prerequest",
                  "script": {
                    "exec": [
                      "if (!pm.collectionVariables.get('ROLE_ID')) {",
                      "    throw new Error('Run RBAC Management / Roles / List Roles or Create Role first so ROLE_ID is available.');",
                      "}"
                    ],
                    "type": "text/javascript",
                    "packages": {},
                    "requests": {}
                  }
                }
              ],
              "request": {
                "method": "GET",
                "header": [
                  { "key": "Accept", "value": "application/json" },
                  { "key": "Authorization", "value": "Bearer {{ADMIN_ACCESS_TOKEN}}" }
                ],
                "url": {
                  "raw": "{{BASE_URL}}/api/v1/admin/roles/{{ROLE_ID}}",
                  "host": ["{{BASE_URL}}"],
                  "path": ["api", "v1", "admin", "roles", "{{ROLE_ID}}"]
                },
                "description": "Retrieves a role by numeric identifier. Requires ROLE_READ permission."
              },
              "response": []
            },
            {
              "name": "Create Role",
              "event": [
                {
                  "listen": "prerequest",
                  "script": {
                    "exec": [
                      "pm.collectionVariables.set('ROLE_NAME', 'Support Agent');",
                      "pm.collectionVariables.set('ROLE_CODE', 'SUPPORT_AGENT');",
                      "pm.collectionVariables.set('ROLE_DESCRIPTION', 'Can read and cancel customer orders.');"
                    ],
                    "type": "text/javascript",
                    "packages": {},
                    "requests": {}
                  }
                },
                {
                  "listen": "test",
                  "script": {
                    "exec": [
                      "const response = pm.response.json();",
                      "if (response.data && response.data.id) {",
                      "    pm.collectionVariables.set('ROLE_ID', response.data.id);",
                      "}"
                    ],
                    "type": "text/javascript",
                    "packages": {},
                    "requests": {}
                  }
                }
              ],
              "request": {
                "method": "POST",
                "header": [
                  { "key": "Content-Type", "value": "application/json" },
                  { "key": "Accept", "value": "application/json" },
                  { "key": "Authorization", "value": "Bearer {{ADMIN_ACCESS_TOKEN}}" }
                ],
                "body": {
                  "mode": "raw",
                  "raw": "{\n  \"name\": \"{{ROLE_NAME}}\",\n  \"code\": \"{{ROLE_CODE}}\",\n  \"description\": \"{{ROLE_DESCRIPTION}}\"\n}"
                },
                "url": {
                  "raw": "{{BASE_URL}}/api/v1/admin/roles",
                  "host": ["{{BASE_URL}}"],
                  "path": ["api", "v1", "admin", "roles"]
                },
                "description": "Creates a new RBAC role. Requires ROLE_CREATE permission. The code field must match a valid RoleCode enum value defined in the service."
              },
              "response": []
            },
            {
              "name": "Update Role",
              "event": [
                {
                  "listen": "prerequest",
                  "script": {
                    "exec": [
                      "if (!pm.collectionVariables.get('ROLE_ID')) {",
                      "    throw new Error('Run Create Role before updating a role so ROLE_ID is available.');",
                      "}",
                      "pm.collectionVariables.set('UPDATED_ROLE_NAME', 'Senior Support Agent');",
                      "pm.collectionVariables.set('UPDATED_ROLE_DESCRIPTION', 'Can read, cancel, and escalate customer orders.');"
                    ],
                    "type": "text/javascript",
                    "packages": {},
                    "requests": {}
                  }
                }
              ],
              "request": {
                "method": "PUT",
                "header": [
                  { "key": "Content-Type", "value": "application/json" },
                  { "key": "Accept", "value": "application/json" },
                  { "key": "Authorization", "value": "Bearer {{ADMIN_ACCESS_TOKEN}}" }
                ],
                "body": {
                  "mode": "raw",
                  "raw": "{\n  \"name\": \"{{UPDATED_ROLE_NAME}}\",\n  \"code\": \"{{ROLE_CODE}}\",\n  \"description\": \"{{UPDATED_ROLE_DESCRIPTION}}\"\n}"
                },
                "url": {
                  "raw": "{{BASE_URL}}/api/v1/admin/roles/{{ROLE_ID}}",
                  "host": ["{{BASE_URL}}"],
                  "path": ["api", "v1", "admin", "roles", "{{ROLE_ID}}"]
                },
                "description": "Updates an existing RBAC role's name and description. Requires ROLE_UPDATE permission."
              },
              "response": []
            },
            {
              "name": "Delete Role",
              "event": [
                {
                  "listen": "prerequest",
                  "script": {
                    "exec": [
                      "if (!pm.collectionVariables.get('ROLE_ID')) {",
                      "    throw new Error('Run Create Role before deleting a role so ROLE_ID is available.');",
                      "}"
                    ],
                    "type": "text/javascript",
                    "packages": {},
                    "requests": {}
                  }
                },
                {
                  "listen": "test",
                  "script": {
                    "exec": [
                      "pm.collectionVariables.unset('ROLE_ID');"
                    ],
                    "type": "text/javascript",
                    "packages": {},
                    "requests": {}
                  }
                }
              ],
              "request": {
                "method": "DELETE",
                "header": [
                  { "key": "Accept", "value": "application/json" },
                  { "key": "Authorization", "value": "Bearer {{ADMIN_ACCESS_TOKEN}}" }
                ],
                "url": {
                  "raw": "{{BASE_URL}}/api/v1/admin/roles/{{ROLE_ID}}",
                  "host": ["{{BASE_URL}}"],
                  "path": ["api", "v1", "admin", "roles", "{{ROLE_ID}}"]
                },
                "description": "Deletes an RBAC role by identifier. Requires ROLE_DELETE permission. ROLE_ID is unset from collection variables on success."
              },
              "response": []
            },
            {
              "name": "Get Role - Not Found",
              "event": [],
              "request": {
                "method": "GET",
                "header": [
                  { "key": "Accept", "value": "application/json" },
                  { "key": "Authorization", "value": "Bearer {{ADMIN_ACCESS_TOKEN}}" }
                ],
                "url": {
                  "raw": "{{BASE_URL}}/api/v1/admin/roles/{{NON_EXISTING_ROLE_ID}}",
                  "host": ["{{BASE_URL}}"],
                  "path": ["api", "v1", "admin", "roles", "{{NON_EXISTING_ROLE_ID}}"]
                },
                "description": "Verifies not-found behavior when requesting a role with an unknown identifier."
              },
              "response": []
            }
          ]
        },
        {
          "name": "Permissions",
          "item": [
            {
              "name": "List Permissions",
              "event": [
                {
                  "listen": "test",
                  "script": {
                    "exec": [
                      "const response = pm.response.json();",
                      "const permissions = response.data && response.data.content ? response.data.content : [];",
                      "const permission = permissions.find(item => item.code === pm.collectionVariables.get('PERMISSION_CODE')) || permissions[0];",
                      "if (permission && permission.id) {",
                      "    pm.collectionVariables.set('PERMISSION_ID', permission.id);",
                      "}"
                    ],
                    "type": "text/javascript",
                    "packages": {},
                    "requests": {}
                  }
                }
              ],
              "request": {
                "method": "GET",
                "header": [
                  { "key": "Accept", "value": "application/json" },
                  { "key": "Authorization", "value": "Bearer {{ADMIN_ACCESS_TOKEN}}" }
                ],
                "url": {
                  "raw": "{{BASE_URL}}/api/v1/admin/permissions?page=0&size=10",
                  "host": ["{{BASE_URL}}"],
                  "path": ["api", "v1", "admin", "permissions"],
                  "query": [
                    { "key": "page", "value": "0" },
                    { "key": "size", "value": "10" }
                  ]
                },
                "description": "Lists RBAC permissions with zero-based pagination. Requires PERMISSION_READ permission. The test script seeds PERMISSION_ID from the first matching result."
              },
              "response": []
            },
            {
              "name": "Get Permission By ID",
              "event": [
                {
                  "listen": "prerequest",
                  "script": {
                    "exec": [
                      "if (!pm.collectionVariables.get('PERMISSION_ID')) {",
                      "    throw new Error('Run RBAC Management / Permissions / List Permissions or Create Permission first so PERMISSION_ID is available.');",
                      "}"
                    ],
                    "type": "text/javascript",
                    "packages": {},
                    "requests": {}
                  }
                }
              ],
              "request": {
                "method": "GET",
                "header": [
                  { "key": "Accept", "value": "application/json" },
                  { "key": "Authorization", "value": "Bearer {{ADMIN_ACCESS_TOKEN}}" }
                ],
                "url": {
                  "raw": "{{BASE_URL}}/api/v1/admin/permissions/{{PERMISSION_ID}}",
                  "host": ["{{BASE_URL}}"],
                  "path": ["api", "v1", "admin", "permissions", "{{PERMISSION_ID}}"]
                },
                "description": "Retrieves a permission by numeric identifier. Requires PERMISSION_READ permission."
              },
              "response": []
            },
            {
              "name": "Create Permission",
              "event": [
                {
                  "listen": "prerequest",
                  "script": {
                    "exec": [
                      "pm.collectionVariables.set('PERMISSION_NAME', 'Read Orders');",
                      "pm.collectionVariables.set('PERMISSION_CODE', 'PERMISSION_ORDER_READ');",
                      "pm.collectionVariables.set('PERMISSION_DESCRIPTION', 'Allows reading customer order data.');"
                    ],
                    "type": "text/javascript",
                    "packages": {},
                    "requests": {}
                  }
                },
                {
                  "listen": "test",
                  "script": {
                    "exec": [
                      "const response = pm.response.json();",
                      "if (response.data && response.data.id) {",
                      "    pm.collectionVariables.set('PERMISSION_ID', response.data.id);",
                      "}"
                    ],
                    "type": "text/javascript",
                    "packages": {},
                    "requests": {}
                  }
                }
              ],
              "request": {
                "method": "POST",
                "header": [
                  { "key": "Content-Type", "value": "application/json" },
                  { "key": "Accept", "value": "application/json" },
                  { "key": "Authorization", "value": "Bearer {{ADMIN_ACCESS_TOKEN}}" }
                ],
                "body": {
                  "mode": "raw",
                  "raw": "{\n  \"name\": \"{{PERMISSION_NAME}}\",\n  \"code\": \"{{PERMISSION_CODE}}\",\n  \"description\": \"{{PERMISSION_DESCRIPTION}}\"\n}"
                },
                "url": {
                  "raw": "{{BASE_URL}}/api/v1/admin/permissions",
                  "host": ["{{BASE_URL}}"],
                  "path": ["api", "v1", "admin", "permissions"]
                },
                "description": "Creates a new RBAC permission. Requires PERMISSION_CREATE permission. The code field must match a valid PermissionCode enum value defined in the service."
              },
              "response": []
            },
            {
              "name": "Update Permission",
              "event": [
                {
                  "listen": "prerequest",
                  "script": {
                    "exec": [
                      "if (!pm.collectionVariables.get('PERMISSION_ID')) {",
                      "    throw new Error('Run Create Permission before updating a permission so PERMISSION_ID is available.');",
                      "}",
                      "pm.collectionVariables.set('UPDATED_PERMISSION_NAME', 'Browse Orders');",
                      "pm.collectionVariables.set('UPDATED_PERMISSION_DESCRIPTION', 'Allows support staff to browse and search customer order data.');"
                    ],
                    "type": "text/javascript",
                    "packages": {},
                    "requests": {}
                  }
                }
              ],
              "request": {
                "method": "PUT",
                "header": [
                  { "key": "Content-Type", "value": "application/json" },
                  { "key": "Accept", "value": "application/json" },
                  { "key": "Authorization", "value": "Bearer {{ADMIN_ACCESS_TOKEN}}" }
                ],
                "body": {
                  "mode": "raw",
                  "raw": "{\n  \"name\": \"{{UPDATED_PERMISSION_NAME}}\",\n  \"code\": \"{{PERMISSION_CODE}}\",\n  \"description\": \"{{UPDATED_PERMISSION_DESCRIPTION}}\"\n}"
                },
                "url": {
                  "raw": "{{BASE_URL}}/api/v1/admin/permissions/{{PERMISSION_ID}}",
                  "host": ["{{BASE_URL}}"],
                  "path": ["api", "v1", "admin", "permissions", "{{PERMISSION_ID}}"]
                },
                "description": "Updates an existing RBAC permission's name and description. Requires PERMISSION_UPDATE permission."
              },
              "response": []
            },
            {
              "name": "Delete Permission",
              "event": [
                {
                  "listen": "prerequest",
                  "script": {
                    "exec": [
                      "if (!pm.collectionVariables.get('PERMISSION_ID')) {",
                      "    throw new Error('Run Create Permission before deleting a permission so PERMISSION_ID is available.');",
                      "}"
                    ],
                    "type": "text/javascript",
                    "packages": {},
                    "requests": {}
                  }
                },
                {
                  "listen": "test",
                  "script": {
                    "exec": [
                      "pm.collectionVariables.unset('PERMISSION_ID');"
                    ],
                    "type": "text/javascript",
                    "packages": {},
                    "requests": {}
                  }
                }
              ],
              "request": {
                "method": "DELETE",
                "header": [
                  { "key": "Accept", "value": "application/json" },
                  { "key": "Authorization", "value": "Bearer {{ADMIN_ACCESS_TOKEN}}" }
                ],
                "url": {
                  "raw": "{{BASE_URL}}/api/v1/admin/permissions/{{PERMISSION_ID}}",
                  "host": ["{{BASE_URL}}"],
                  "path": ["api", "v1", "admin", "permissions", "{{PERMISSION_ID}}"]
                },
                "description": "Deletes an RBAC permission by identifier. Requires PERMISSION_DELETE permission. PERMISSION_ID is unset from collection variables on success."
              },
              "response": []
            },
            {
              "name": "Get Permission - Not Found",
              "event": [],
              "request": {
                "method": "GET",
                "header": [
                  { "key": "Accept", "value": "application/json" },
                  { "key": "Authorization", "value": "Bearer {{ADMIN_ACCESS_TOKEN}}" }
                ],
                "url": {
                  "raw": "{{BASE_URL}}/api/v1/admin/permissions/{{NON_EXISTING_PERMISSION_ID}}",
                  "host": ["{{BASE_URL}}"],
                  "path": ["api", "v1", "admin", "permissions", "{{NON_EXISTING_PERMISSION_ID}}"]
                },
                "description": "Verifies not-found behavior when requesting a permission with an unknown identifier."
              },
              "response": []
            }
          ]
        },
        {
          "name": "Role Permission Assignment",
          "item": [
            {
              "name": "List Role Permissions",
              "event": [
                {
                  "listen": "prerequest",
                  "script": {
                    "exec": [
                      "if (!pm.collectionVariables.get('ROLE_ID')) {",
                      "    throw new Error('Run RBAC Management / Roles / Create Role first so ROLE_ID is available.');",
                      "}"
                    ],
                    "type": "text/javascript",
                    "packages": {},
                    "requests": {}
                  }
                }
              ],
              "request": {
                "method": "GET",
                "header": [
                  { "key": "Accept", "value": "application/json" },
                  { "key": "Authorization", "value": "Bearer {{ADMIN_ACCESS_TOKEN}}" }
                ],
                "url": {
                  "raw": "{{BASE_URL}}/api/v1/admin/roles/{{ROLE_ID}}/permissions",
                  "host": ["{{BASE_URL}}"],
                  "path": ["api", "v1", "admin", "roles", "{{ROLE_ID}}", "permissions"]
                },
                "description": "Lists all permissions currently assigned to a role. Requires ROLE_READ permission."
              },
              "response": []
            },
            {
              "name": "Assign Permission To Role",
              "event": [
                {
                  "listen": "prerequest",
                  "script": {
                    "exec": [
                      "if (!pm.collectionVariables.get('ROLE_ID')) {",
                      "    throw new Error('Run Create Role before assigning a permission so ROLE_ID is available.');",
                      "}",
                      "if (!pm.collectionVariables.get('PERMISSION_ID')) {",
                      "    throw new Error('Run Create Permission before assigning it to a role so PERMISSION_ID is available.');",
                      "}"
                    ],
                    "type": "text/javascript",
                    "packages": {},
                    "requests": {}
                  }
                }
              ],
              "request": {
                "method": "POST",
                "header": [
                  { "key": "Accept", "value": "application/json" },
                  { "key": "Authorization", "value": "Bearer {{ADMIN_ACCESS_TOKEN}}" }
                ],
                "url": {
                  "raw": "{{BASE_URL}}/api/v1/admin/roles/{{ROLE_ID}}/permissions/{{PERMISSION_ID}}",
                  "host": ["{{BASE_URL}}"],
                  "path": ["api", "v1", "admin", "roles", "{{ROLE_ID}}", "permissions", "{{PERMISSION_ID}}"]
                },
                "description": "Assigns a permission to a role. Requires ROLE_CREATE permission. Returns the updated role with its full permission list."
              },
              "response": []
            },
            {
              "name": "Remove Permission From Role",
              "event": [
                {
                  "listen": "prerequest",
                  "script": {
                    "exec": [
                      "if (!pm.collectionVariables.get('ROLE_ID')) {",
                      "    throw new Error('Run Create Role before removing a permission so ROLE_ID is available.');",
                      "}",
                      "if (!pm.collectionVariables.get('PERMISSION_ID')) {",
                      "    throw new Error('Run Assign Permission To Role before removing a permission so PERMISSION_ID is available.');",
                      "}"
                    ],
                    "type": "text/javascript",
                    "packages": {},
                    "requests": {}
                  }
                }
              ],
              "request": {
                "method": "DELETE",
                "header": [
                  { "key": "Accept", "value": "application/json" },
                  { "key": "Authorization", "value": "Bearer {{ADMIN_ACCESS_TOKEN}}" }
                ],
                "url": {
                  "raw": "{{BASE_URL}}/api/v1/admin/roles/{{ROLE_ID}}/permissions/{{PERMISSION_ID}}",
                  "host": ["{{BASE_URL}}"],
                  "path": ["api", "v1", "admin", "roles", "{{ROLE_ID}}", "permissions", "{{PERMISSION_ID}}"]
                },
                "description": "Removes a permission from a role. Requires ROLE_DELETE permission. Returns the updated role with its remaining permission list."
              },
              "response": []
            }
          ]
        },
        {
          "name": "User Role Assignment",
          "item": [
            {
              "name": "List User Roles",
              "event": [
                {
                  "listen": "prerequest",
                  "script": {
                    "exec": [
                      "if (!pm.collectionVariables.get('AUTH_USER_ID')) {",
                      "    throw new Error('Run Authentication / Register User or User Profile / Happy Path / Get Current User Profile first so AUTH_USER_ID is available.');",
                      "}"
                    ],
                    "type": "text/javascript",
                    "packages": {},
                    "requests": {}
                  }
                }
              ],
              "request": {
                "method": "GET",
                "header": [
                  { "key": "Accept", "value": "application/json" },
                  { "key": "Authorization", "value": "Bearer {{ADMIN_ACCESS_TOKEN}}" }
                ],
                "url": {
                  "raw": "{{BASE_URL}}/api/v1/admin/users/{{AUTH_USER_ID}}/roles",
                  "host": ["{{BASE_URL}}"],
                  "path": ["api", "v1", "admin", "users", "{{AUTH_USER_ID}}", "roles"]
                },
                "description": "Lists all roles currently assigned to a user. Requires ROLE_ASSIGN permission."
              },
              "response": []
            },
            {
              "name": "Assign Role To User",
              "event": [
                {
                  "listen": "prerequest",
                  "script": {
                    "exec": [
                      "if (!pm.collectionVariables.get('AUTH_USER_ID')) {",
                      "    throw new Error('Run Authentication / Register User first so AUTH_USER_ID is available.');",
                      "}",
                      "if (!pm.collectionVariables.get('ROLE_ID')) {",
                      "    throw new Error('Run RBAC Management / Roles / Create Role first so ROLE_ID is available.');",
                      "}"
                    ],
                    "type": "text/javascript",
                    "packages": {},
                    "requests": {}
                  }
                }
              ],
              "request": {
                "method": "POST",
                "header": [
                  { "key": "Accept", "value": "application/json" },
                  { "key": "Authorization", "value": "Bearer {{ADMIN_ACCESS_TOKEN}}" }
                ],
                "url": {
                  "raw": "{{BASE_URL}}/api/v1/admin/users/{{AUTH_USER_ID}}/roles/{{ROLE_ID}}",
                  "host": ["{{BASE_URL}}"],
                  "path": ["api", "v1", "admin", "users", "{{AUTH_USER_ID}}", "roles", "{{ROLE_ID}}"]
                },
                "description": "Assigns a role to a user. Requires ROLE_ASSIGN permission. Returns the complete list of roles now held by the user."
              },
              "response": []
            },
            {
              "name": "Remove Role From User",
              "event": [
                {
                  "listen": "prerequest",
                  "script": {
                    "exec": [
                      "if (!pm.collectionVariables.get('AUTH_USER_ID')) {",
                      "    throw new Error('Run Authentication / Register User first so AUTH_USER_ID is available.');",
                      "}",
                      "if (!pm.collectionVariables.get('ROLE_ID')) {",
                      "    throw new Error('Run Assign Role To User before removing a role so ROLE_ID is available.');",
                      "}"
                    ],
                    "type": "text/javascript",
                    "packages": {},
                    "requests": {}
                  }
                }
              ],
              "request": {
                "method": "DELETE",
                "header": [
                  { "key": "Accept", "value": "application/json" },
                  { "key": "Authorization", "value": "Bearer {{ADMIN_ACCESS_TOKEN}}" }
                ],
                "url": {
                  "raw": "{{BASE_URL}}/api/v1/admin/users/{{AUTH_USER_ID}}/roles/{{ROLE_ID}}",
                  "host": ["{{BASE_URL}}"],
                  "path": ["api", "v1", "admin", "users", "{{AUTH_USER_ID}}", "roles", "{{ROLE_ID}}"]
                },
                "description": "Removes a role from a user. Requires ROLE_ASSIGN permission. Returns the remaining roles held by the user after removal."
              },
              "response": []
            },
            {
              "name": "Assign Role To User - User Not Found",
              "event": [],
              "request": {
                "method": "POST",
                "header": [
                  { "key": "Accept", "value": "application/json" },
                  { "key": "Authorization", "value": "Bearer {{ADMIN_ACCESS_TOKEN}}" }
                ],
                "url": {
                  "raw": "{{BASE_URL}}/api/v1/admin/users/{{NON_EXISTING_USER_ID}}/roles/{{ROLE_ID}}",
                  "host": ["{{BASE_URL}}"],
                  "path": ["api", "v1", "admin", "users", "{{NON_EXISTING_USER_ID}}", "roles", "{{ROLE_ID}}"]
                },
                "description": "Verifies not-found behavior when assigning a role to an unknown user identifier."
              },
              "response": []
            }
          ]
        }
      ]
    }
  ],
  "event": [
    {
      "listen": "prerequest",
      "script": {
        "type": "text/javascript",
        "exec": [
          "pm.collectionVariables.set('NON_EXISTING_ROLE_ID', pm.collectionVariables.get('NON_EXISTING_ROLE_ID') || '999999999');",
          "pm.collectionVariables.set('NON_EXISTING_PERMISSION_ID', pm.collectionVariables.get('NON_EXISTING_PERMISSION_ID') || '999999999');",
          "pm.collectionVariables.set('NON_EXISTING_USER_ID', pm.collectionVariables.get('NON_EXISTING_USER_ID') || '999999999');"
        ]
      }
    }
  ],
  "variable": [
    {
      "key": "BASE_URL",
      "value": "http://localhost:8080"
    },
    {
      "key": "ACCESS_TOKEN",
      "value": ""
    },
    {
      "key": "REFRESH_TOKEN",
      "value": ""
    },
    {
      "key": "TOKEN_TYPE",
      "value": "Bearer"
    },
    {
      "key": "ADMIN_USERNAME",
      "value": "admin"
    },
    {
      "key": "ADMIN_PASSWORD",
      "value": "StrongPass123"
    },
    {
      "key": "ADMIN_ACCESS_TOKEN",
      "value": ""
    },
    {
      "key": "ADMIN_REFRESH_TOKEN",
      "value": ""
    },
    {
      "key": "AUTH_USER_ID",
      "value": ""
    },
    {
      "key": "AUTH_FIRST_NAME",
      "value": "Pial"
    },
    {
      "key": "AUTH_LAST_NAME",
      "value": "Samadder"
    },
    {
      "key": "AUTH_USERNAME",
      "value": ""
    },
    {
      "key": "AUTH_EMAIL",
      "value": ""
    },
    {
      "key": "AUTH_PHONE_NUMBER",
      "value": "+8801700000000"
    },
    {
      "key": "AUTH_PASSWORD",
      "value": "StrongPass123"
    },
    {
      "key": "UPDATED_FIRST_NAME",
      "value": "PialUpdated"
    },
    {
      "key": "UPDATED_PHONE_NUMBER",
      "value": "+8801711111111"
    },
    {
      "key": "ROLE_ID",
      "value": ""
    },
    {
      "key": "ROLE_NAME",
      "value": "Support Agent"
    },
    {
      "key": "ROLE_CODE",
      "value": "SUPPORT_AGENT"
    },
    {
      "key": "ROLE_DESCRIPTION",
      "value": "Can read and cancel customer orders."
    },
    {
      "key": "UPDATED_ROLE_NAME",
      "value": "Senior Support Agent"
    },
    {
      "key": "UPDATED_ROLE_DESCRIPTION",
      "value": "Can read, cancel, and escalate customer orders."
    },
    {
      "key": "NON_EXISTING_ROLE_ID",
      "value": "999999999"
    },
    {
      "key": "PERMISSION_ID",
      "value": ""
    },
    {
      "key": "PERMISSION_NAME",
      "value": "Read Orders"
    },
    {
      "key": "PERMISSION_CODE",
      "value": "PERMISSION_ORDER_READ"
    },
    {
      "key": "PERMISSION_DESCRIPTION",
      "value": "Allows reading customer order data."
    },
    {
      "key": "UPDATED_PERMISSION_NAME",
      "value": "Browse Orders"
    },
    {
      "key": "UPDATED_PERMISSION_DESCRIPTION",
      "value": "Allows support staff to browse and search customer order data."
    },
    {
      "key": "NON_EXISTING_PERMISSION_ID",
      "value": "999999999"
    },
    {
      "key": "NON_EXISTING_USER_ID",
      "value": "999999999"
    }
  ]
}
